tot_minus/__init__.py
tot_minus/minus.py
tot_minus-0.1.7.dist-info/METADATA
tot_minus-0.1.7.dist-info/WHEEL
tot_minus-0.1.7.dist-info/entry_points.txt
tot_minus-0.1.7.dist-info/top_level.txt
tot_minus-0.1.7.dist-info/RECORD
