Metadata-Version: 2.1
Name: tot_minus
Version: 0.1.7
Summary: Default template for PDM package
Author-email: DONGUK777 <kimdongyork@gmail.com>
License: MIT
Requires-Python: >=3.9
